{"action":"whoami","duration_ms":0,"error":null,"error_code":null,"input":{"arguments":{"action":"whoami"},"name":"session"},"method":"tools/call","output":{"content":[{"text":"{\"scope\":\"personal\",\"permissions\":[],\"user_id\":null,\"org_id\":null}","type":"text"}]},"request_id":"req_019c3807-a284-7064-af38-71ffd74ec04c","routed_to":"sanctum","session_id":"sess_019c3807-a284-7970-93c7-68b8945c3a92","status":"success","timestamp":"2026-02-07T12:15:50.404698Z","tool":"session","user_id":null}